craftr/dsl/__init__.py
craftr/dsl/__main__.py
craftr/dsl/_execute.py
craftr/dsl/_rewriter.py
craftr/dsl/_runtime.py
craftr/dsl/_transpiler.py
craftr/dsl/_util.py
craftr/dsl/ast_utils.py
craftr/dsl/py.typed
craftr_dsl-0.9.0.dist-info/LICENSE
craftr_dsl-0.9.0.dist-info/WHEEL
craftr_dsl-0.9.0.dist-info/METADATA
craftr_dsl-0.9.0.dist-info/RECORD
