Metadata-Version: 2.1
Name: craftr-dsl
Version: 0.9.0
Summary: Domain specific language for the Craftr build system.
License: MIT
Author: Niklas Rosenstein
Author-email: rosensteinniklas@gmail.com
Requires-Python: >=3.7,<4.0
Classifier: License :: OSI Approved :: MIT License
Classifier: Programming Language :: Python :: 3
Classifier: Programming Language :: Python :: 3.7
Classifier: Programming Language :: Python :: 3.8
Classifier: Programming Language :: Python :: 3.9
Classifier: Programming Language :: Python :: 3.10
Provides-Extra: astor
Requires-Dist: nr.util (>=0.7.0,<1.0.0)
Requires-Dist: termcolor (>=1.1.0,<2.0.0)
Requires-Dist: typing-extensions (>=3.0.0)
Project-URL: Documentation, https://niklasrosenstein.github.io/craftr-dsl/
Project-URL: Homepage, https://github.com/NiklasRosenstein/craftr-dsl
